bloscpack/__init__.py
bloscpack/abstract_io.py
bloscpack/abstract_objects.py
bloscpack/append.py
bloscpack/args.py
bloscpack/checksums.py
bloscpack/cli.py
bloscpack/compat_util.py
bloscpack/constants.py
bloscpack/defaults.py
bloscpack/exceptions.py
bloscpack/file_io.py
bloscpack/headers.py
bloscpack/highlevel.py
bloscpack/log.py
bloscpack/memory_io.py
bloscpack/metacodecs.py
bloscpack/numpy_io.py
bloscpack/pretty.py
bloscpack/serializers.py
bloscpack/sysutil.py
bloscpack/testutil.py
bloscpack/util.py
bloscpack/version.py
bloscpack-0.16.0.dist-info/DESCRIPTION.rst
bloscpack-0.16.0.dist-info/METADATA
bloscpack-0.16.0.dist-info/RECORD
bloscpack-0.16.0.dist-info/WHEEL
bloscpack-0.16.0.dist-info/entry_points.txt
bloscpack-0.16.0.dist-info/metadata.json
bloscpack-0.16.0.dist-info/top_level.txt
