Metadata-Version: 2.0
Name: bloscpack
Version: 0.16.0
Summary: Command line interface to and serialization format for Blosc
Home-page: https://github.com/blosc/bloscpack
Author: Valentin Haenel
Author-email: valentin@haenel.co
License: MIT
Keywords: compression,applied information theory
Platform: UNKNOWN
Classifier: Development Status :: 4 - Beta
Classifier: Environment :: Console
Classifier: License :: OSI Approved :: MIT License
Classifier: Operating System :: Microsoft :: Windows
Classifier: Operating System :: POSIX
Classifier: Programming Language :: Python
Classifier: Topic :: Scientific/Engineering
Classifier: Topic :: System :: Archiving :: Compression
Classifier: Topic :: Utilities
Classifier: Programming Language :: Python
Classifier: Programming Language :: Python :: 2.7
Classifier: Programming Language :: Python :: 3.4
Classifier: Programming Language :: Python :: 3.5
Classifier: Programming Language :: Python :: 3.6
Classifier: Programming Language :: Python :: 3.7
Provides-Extra: tests
Requires-Dist: blosc
Requires-Dist: numpy
Requires-Dist: six
Requires-Dist: deprecated
Provides-Extra: tests
Requires-Dist: nose; extra == 'tests'
Requires-Dist: cram (>=0.6); extra == 'tests'
Requires-Dist: mock; extra == 'tests'
Requires-Dist: coverage; extra == 'tests'
Requires-Dist: coveralls; extra == 'tests'
Requires-Dist: twine; extra == 'tests'
Requires-Dist: wheel; extra == 'tests'
